hi_lasso2/__init__.py
hi_lasso2/glmnet_model.py
hi_lasso2/hi_lasso2.py
hi_lasso2/util.py
hi_lasso2-0.0.1.dist-info/METADATA
hi_lasso2-0.0.1.dist-info/WHEEL
hi_lasso2-0.0.1.dist-info/top_level.txt
hi_lasso2-0.0.1.dist-info/RECORD
