Metadata-Version: 2.1
Name: hi-lasso2
Version: 0.0.1
Summary: High-Demensional LASSO2
Home-page: https://github.com/datax-lab/Hi-LASSO2
Author: Beomsu Baek
Author-email: qorqjatn1388@gnu.ac.kr
Keywords: variable selection,feature selection,lasso,high-dimensional data
Classifier: Programming Language :: Python :: 3.6
Classifier: License :: OSI Approved :: MIT License
Classifier: Operating System :: OS Independent
Requires-Python: >=3.6
Requires-Dist: glmnet
Requires-Dist: tqdm
